pyspotter/__init__.py
pyspotter/pyspotter.py
pyspotter-0.0.7.dist-info/LICENSE
pyspotter-0.0.7.dist-info/METADATA
pyspotter-0.0.7.dist-info/WHEEL
pyspotter-0.0.7.dist-info/entry_points.txt
pyspotter-0.0.7.dist-info/top_level.txt
pyspotter-0.0.7.dist-info/RECORD
