Metadata-Version: 2.1
Name: pyspotter
Version: 0.0.7
Summary: Simple CLI for SofarOcean API
Home-page: https://github.com/samapriya/pyspotter
Author: Samapriya Roy
Author-email: samapriya.roy@gmail.com
License: MIT
Classifier: Intended Audience :: Developers
Classifier: Intended Audience :: Science/Research
Classifier: Natural Language :: English
Classifier: License :: OSI Approved :: MIT License
Classifier: Programming Language :: Python :: 3.6
Classifier: Programming Language :: Python :: 3.7
Classifier: Operating System :: OS Independent
Classifier: Topic :: Scientific/Engineering :: GIS
License-File: LICENSE
Requires-Dist: requests >=2.23.1
Requires-Dist: timezonefinder >=5.2.0
Requires-Dist: pytz >=2020.1
Requires-Dist: beautifulsoup4 >=4.9.3
Requires-Dist: pandas >=2.1.2
Requires-Dist: python-dateutil >=2.8.2
